pixelpay/__init__.py
pixelpay/assets/countries.json
pixelpay/assets/formats.json
pixelpay/assets/states.json
pixelpay/base/Helpers.py
pixelpay/base/RequestBehaviour.py
pixelpay/base/Response.py
pixelpay/base/ServiceBehaviour.py
pixelpay/base/__init__.py
pixelpay/entities/CardResult.py
pixelpay/entities/TransactionResult.py
pixelpay/entities/__init__.py
pixelpay/exceptions/InvalidCredentialsException.py
pixelpay/exceptions/InvalidTransactionTypeException.py
pixelpay/exceptions/__init__.py
pixelpay/libraries/RouterManager.py
pixelpay/libraries/__init__.py
pixelpay/models/Billing.py
pixelpay/models/Card.py
pixelpay/models/Item.py
pixelpay/models/Order.py
pixelpay/models/Settings.py
pixelpay/models/__init__.py
pixelpay/requests/AuthTransaction.py
pixelpay/requests/CaptureTransaction.py
pixelpay/requests/CardTokenization.py
pixelpay/requests/PaymentTransaction.py
pixelpay/requests/SaleTransaction.py
pixelpay/requests/StatusTransaction.py
pixelpay/requests/VoidTransaction.py
pixelpay/requests/__init__.py
pixelpay/resources/Environment.py
pixelpay/resources/Locations.py
pixelpay/resources/__init__.py
pixelpay/responses/ErrorResponse.py
pixelpay/responses/FailureResponse.py
pixelpay/responses/InputErrorResponse.py
pixelpay/responses/NetworkFailureResponse.py
pixelpay/responses/NoAccessResponse.py
pixelpay/responses/NotFoundResponse.py
pixelpay/responses/PayloadResponse.py
pixelpay/responses/PaymentDeclinedResponse.py
pixelpay/responses/PreconditionalResponse.py
pixelpay/responses/SuccessResponse.py
pixelpay/responses/TimeoutResponse.py
pixelpay/responses/__init__.py
pixelpay/services/Tokenization.py
pixelpay/services/Transaction.py
pixelpay/services/__init__.py
pixelpay_sdk-2.2.5.dist-info/licenses/LICENSE.md
pixelpay_sdk-2.2.5.dist-info/METADATA
pixelpay_sdk-2.2.5.dist-info/WHEEL
pixelpay_sdk-2.2.5.dist-info/top_level.txt
pixelpay_sdk-2.2.5.dist-info/RECORD
